my_data_lib/__init__.py
my_data_lib/csv_handler.py
my_data_lib/factory.py
my_data_lib/logger.py
my_data_lib/mongodb_handler.py
my_data_lib/postgres_handler.py
my_data_lib-0.1.3.dist-info/METADATA
my_data_lib-0.1.3.dist-info/WHEEL
my_data_lib-0.1.3.dist-info/top_level.txt
my_data_lib-0.1.3.dist-info/RECORD
