Metadata-Version: 2.4
Name: my_data_lib
Version: 0.1.3
Summary: Uma biblioteca para manipulação de dados em diferentes fontes
Author-email: Gugpo <poliveiragpo@gmail.com>
Requires-Python: >=3.13.3
Requires-Dist: pandas==2.2.3
Requires-Dist: sqlalchemy==2.0.41
Requires-Dist: psycopg2==2.9.10
Requires-Dist: pymongo==4.13.0
Requires-Dist: pytest==8.4.0
